{"TFT3_Ahri,TFT3_Annie,TFT3_Fizz,TFT3_Gangplank,TFT3_Rumble,TFT3_Syndra,TFT3_Viktor,TFT3_Xerath,TFT3_Zoe":{"bottom4Percentage":0.44680851063829785,"compName":"Mech-Pilot, Sorcerer, Star Guardian","placements":[4,5,2,6,6,3,6,1,2,5,3,1,1,3,4,5,5,2,4,4,2,2,5,3,1,1,5,3,2,2,2,1,3,1,1,3,3,2,2,2,3,4,1,1,4,1,5,3,1,6,3,2,1,8,2,2,3,5,6,3,1,2,5,3,2,2,1,1,3,3,1,3,5,3,7,2,3,1,1,3,1,2,2,1,6,4,3,1,3,3,4,5,1,6,2,2,2,4,2,1,1,4,1,4,5,1,4,6,3,7,1,1,1,6,1,3,5,5,2,1,7,2,2,3,3,2,3,6,3,6,3,3,1,4,6,1,2,2,2,1,3],"top4Percentage":0.5531914893617021,"traits":[{"name":"Battlecast","num_units":1,"style":0,"tier_current":0,"tier_total":4},{"name":"DarkStar","num_units":1,"style":0,"tier_current":0,"tier_total":4},{"name":"Demolitionist","num_units":2,"style":3,"tier_current":1,"tier_total":1},{"name":"Infiltrator","num_units":1,"style":0,"tier_current":0,"tier_total":3},{"name":"MechPilot","num_units":3,"style":3,"tier_current":1,"tier_total":1},{"name":"Mercenary","num_units":1,"style":3,"tier_current":1,"tier_total":1},{"name":"Set3_Sorcerer","num_units":6,"style":3,"tier_current":3,"tier_total":3},{"name":"SpacePirate","num_units":1,"style":0,"tier_current":0,"tier_total":2},{"name":"StarGuardian","num_units":4,"style":1,"tier_current":1,"tier_total":3}],"units":[{"character_id":"TFT3_Zoe","items":[14],"name":"","rarity":0,"tier":2},{"character_id":"TFT3_Ahri","items":[],"name":"","rarity":1,"tier":2},{"character_id":"TFT3_Annie","items":[36],"name":"","rarity":1,"tier":2},{"character_id":"TFT3_Rumble","items":[69,25],"name":"","rarity":2,"tier":2},{"character_id":"TFT3_Syndra","items":[],"name":"","rarity":2,"tier":2},{"character_id":"TFT3_Fizz","items":[],"name":"","rarity":3,"tier":1},{"character_id":"TFT3_Viktor","items":[48,37,12],"name":"","rarity":3,"tier":2},{"character_id":"TFT3_Gangplank","items":[15],"name":"","rarity":4,"tier":1},{"character_id":"TFT3_Xerath","items":[7],"name":"","rarity":4,"tier":2}],"winPercentage":0.24822695035460993},"TFT3_Ashe,TFT3_Caitlyn,TFT3_Gnar,TFT3_Jhin,TFT3_Karma,TFT3_Lulu,TFT3_Nautilus,TFT3_Teemo,TFT3_WuKong":{"bottom4Percentage":0.37566137566137564,"compName":"Astro, Sniper","placements":[2,4,1,4,1,1,4,2,6,4,2,2,3,5,4,7,3,3,1,2,4,4,5,2,4,7,1,3,3,1,3,5,6,3,5,2,3,3,4,3,1,1,5,2,1,1,2,4,3,6,1,1,2,2,5,4,2,3,7,4,4,2,3,2,2,1,1,2,2,1,4,3,1,2,5,2,3,1,1,6,1,5,5,6,2,2,2,1,6,2,4,1,4,7,1,1,5,2,1,1,3,2,3,2,4,1,1,2,4,6,4,1,6,5,6,3,1,1,2,6,1,3,5,3,4,6,1,2,4,2,2,5,1,1,8,4,6,3,1,4,3,2,2,1,3,3,3,2,6,1,1,2,3,4,3,1,1,1,7,1,1,4,1,3,5,3,1,2,3,4,1,2,1,1,5,2,4,1,2,8,1,3,3,1,1,8,1,1,1],"top4Percentage":0.6243386243386243,"traits":[{"name":"Astro","num_units":3,"style":3,"tier_current":1,"tier_total":1},{"name":"Chrono","num_units":2,"style":1,"tier_current":1,"tier_total":4},{"name":"DarkStar","num_units":2,"style":1,"tier_current":1,"tier_total":4},{"name":"Set3_Brawler","num_units":1,"style":0,"tier_current":0,"tier_total":2},{"name":"Set3_Celestial","num_units":2,"style":1,"tier_current":1,"tier_total":3},{"name":"Set3_Mystic","num_units":2,"style":1,"tier_current":1,"tier_total":2},{"name":"Sniper","num_units":4,"style":3,"tier_current":2,"tier_total":2},{"name":"Vanguard","num_units":2,"style":1,"tier_current":1,"tier_total":3}],"units":[{"character_id":"TFT3_Caitlyn","items":[],"name":"","rarity":0,"tier":1},{"character_id":"TFT3_Nautilus","items":[],"name":"","rarity":1,"tier":2},{"character_id":"TFT3_Ashe","items":[29,1],"name":"","rarity":2,"tier":2},{"character_id":"TFT3_Karma","items":[],"name":"","rarity":2,"tier":1},{"character_id":"TFT3_Jhin","items":[26,29,19],"name":"","rarity":3,"tier":3},{"character_id":"TFT3_WuKong","items":[],"name":"","rarity":3,"tier":2},{"character_id":"TFT3_Gnar","items":[79,56,15],"name":"","rarity":3,"tier":2},{"character_id":"TFT3_Teemo","items":[44,37,33],"name":"","rarity":3,"tier":2},{"character_id":"TFT3_Lulu","items":[],"name":"","rarity":4,"tier":2}],"winPercentage":0.291005291005291},"TFT3_Ashe,TFT3_Ekko,TFT3_Fiora,TFT3_Irelia,TFT3_Leona,TFT3_Thresh,TFT3_Vayne,TFT3_Vi,TFT3_WuKong":{"bottom4Percentage":0.3933333333333333,"compName":"Cybernetic","placements":[2,2,2,1,1,7,1,1,1,2,1,3,3,1,1,7,1,2,1,2,3,2,4,2,1,4,1,2,1,4,1,3,3,2,1,4,2,6,1,6,1,1,3,4,1,1,4,1,2,1,2,4,3,1,4,3,4,5,2,3,1,2,5,3,1,3,1,3,3,3,6,4,1,2,2,2,5,1,3,1,2,2,4,6,6,3,3,1,1,2,3,5,4,3,3,2,1,1,1,1,2,1,5,1,1,1,4,5,1,3,1,3,5,1,3,4,1,2,2,5,1,2,1,5,2,1,1,1,7,2,1,1,2,5,5,1,3,1,1,5,2,3,1,3,4,2,4,1,2,3],"top4Percentage":0.6066666666666667,"traits":[{"name":"Chrono","num_units":2,"style":1,"tier_current":1,"tier_total":4},{"name":"Cybernetic","num_units":6,"style":3,"tier_current":2,"tier_total":2},{"name":"Infiltrator","num_units":1,"style":0,"tier_current":0,"tier_total":3},{"name":"ManaReaver","num_units":2,"style":3,"tier_current":1,"tier_total":1},{"name":"Set3_Blademaster","num_units":2,"style":0,"tier_current":0,"tier_total":3},{"name":"Set3_Brawler","num_units":1,"style":0,"tier_current":0,"tier_total":2},{"name":"Set3_Celestial","num_units":1,"style":0,"tier_current":0,"tier_total":3},{"name":"Sniper","num_units":2,"style":1,"tier_current":1,"tier_total":2},{"name":"Vanguard","num_units":2,"style":1,"tier_current":1,"tier_total":3}],"units":[{"character_id":"TFT3_Fiora","items":[47],"name":"","rarity":0,"tier":2},{"character_id":"TFT3_Leona","items":[36],"name":"","rarity":0,"tier":1},{"character_id":"TFT3_Vi","items":[45],"name":"","rarity":2,"tier":2},{"character_id":"TFT3_Ashe","items":[],"name":"","rarity":2,"tier":1},{"character_id":"TFT3_Vayne","items":[29,25],"name":"","rarity":2,"tier":2},{"character_id":"TFT3_Irelia","items":[16],"name":"","rarity":3,"tier":2},{"character_id":"TFT3_WuKong","items":[],"name":"","rarity":3,"tier":2},{"character_id":"TFT3_Thresh","items":[44],"name":"","rarity":4,"tier":2},{"character_id":"TFT3_Ekko","items":[23,24],"name":"","rarity":4,"tier":2}],"winPercentage":0.36666666666666664},"TFT3_AurelionSol,TFT3_Blitzcrank,TFT3_Ezreal,TFT3_Gnar,TFT3_Jinx,TFT3_Lulu,TFT3_Malphite,TFT3_Soraka,TFT3_Vi":{"bottom4Percentage":0.40268456375838924,"compName":"Rebel, Brawler","placements":[1,4,4,2,2,3,4,3,6,2,1,2,1,4,1,1,4,1,1,1,1,6,5,4,2,3,1,1,2,4,4,1,1,1,4,2,1,1,2,4,2,2,2,3,2,1,4,1,3,1,4,1,5,2,2,2,3,3,2,1,3,1,4,3,3,2,4,1,5,1,2,1,1,1,3,3,1,4,2,2,4,4,1,1,4,4,3,3,4,1,1,4,1,3,5,4,4,2,3,3,1,1,1,5,5,3,2,3,3,1,2,2,2,2,2,1,2,2,3,1,4,2,7,1,2,2,1,7,7,2,5,4,3,4,1,1,1,7,1,2,1,2,5,1,2,2,1,8,2],"top4Percentage":0.5973154362416108,"traits":[{"name":"Astro","num_units":1,"style":0,"tier_current":0,"tier_total":1},{"name":"Battlecast","num_units":1,"style":0,"tier_current":0,"tier_total":4},{"name":"Blaster","num_units":2,"style":1,"tier_current":1,"tier_total":2},{"name":"Chrono","num_units":2,"style":1,"tier_current":1,"tier_total":4},{"name":"Cybernetic","num_units":1,"style":0,"tier_current":0,"tier_total":2},{"name":"Rebel","num_units":3,"style":1,"tier_current":1,"tier_total":3},{"name":"Set3_Brawler","num_units":4,"style":3,"tier_current":2,"tier_total":2},{"name":"Set3_Celestial","num_units":1,"style":0,"tier_current":0,"tier_total":3},{"name":"Set3_Mystic","num_units":2,"style":1,"tier_current":1,"tier_total":2},{"name":"StarGuardian","num_units":1,"style":0,"tier_current":0,"tier_total":3},{"name":"Starship","num_units":1,"style":3,"tier_current":1,"tier_total":1}],"units":[{"character_id":"TFT3_Malphite","items":[],"name":"","rarity":0,"tier":2},{"character_id":"TFT3_Blitzcrank","items":[],"name":"","rarity":1,"tier":2},{"character_id":"TFT3_Ezreal","items":[44,57],"name":"","rarity":2,"tier":2},{"character_id":"TFT3_Vi","items":[6],"name":"","rarity":2,"tier":2},{"character_id":"TFT3_Jinx","items":[29,12,19],"name":"","rarity":3,"tier":2},{"character_id":"TFT3_Soraka","items":[59],"name":"","rarity":3,"tier":2},{"character_id":"TFT3_Gnar","items":[66,35],"name":"","rarity":3,"tier":2},{"character_id":"TFT3_AurelionSol","items":[38],"name":"","rarity":4,"tier":2},{"character_id":"TFT3_Lulu","items":[],"name":"","rarity":4,"tier":2}],"winPercentage":0.3221476510067114},"TFT3_Bard,TFT3_Cassiopeia,TFT3_Jayce,TFT3_Karma,TFT3_Mordekaiser,TFT3_Nautilus,TFT3_Soraka,TFT3_WuKong":{"bottom4Percentage":0.08860759493670886,"compName":"Mystic, Vanguard","placements":[6,5,5,7,2,2,7,7,5,8,8,4,5,7,7,8,2,7,8,7,5,5,6,5,6,6,4,5,4,3,8,7,7,6,7,8,6,8,5,7,8,7,7,6,5,6,7,8,8,8,6,6,6,6,3,4,5,7,4,6,4,6,8,3,8,5,4,5,5,8,7,4,6,5,5,8,5,8,8,7,7,4,7,7,6,8,3,6,3,7,6,8,5,6,4,8,7,4,6,5,5,6,3,7,4,4,5,3,6,7,4,4,6,8,8,4,7,7,8,5,7,5,7,6,8,7,6,4,3,5,8,3,7,5,1,6,7,8,3,8,7,3,7,7,8,5,7,5,6,8,8,4,7,5,7,6,8,7],"top4Percentage":0.9113924050632911,"traits":[{"name":"Astro","num_units":2,"style":0,"tier_current":0,"tier_total":1},{"name":"Battlecast","num_units":1,"style":0,"tier_current":0,"tier_total":4},{"name":"Chrono","num_units":1,"style":0,"tier_current":0,"tier_total":4},{"name":"DarkStar","num_units":2,"style":1,"tier_current":1,"tier_total":4},{"name":"Set3_Mystic","num_units":4,"style":3,"tier_current":2,"tier_total":2},{"name":"SpacePirate","num_units":1,"style":0,"tier_current":0,"tier_total":2},{"name":"StarGuardian","num_units":1,"style":0,"tier_current":0,"tier_total":3},{"name":"Vanguard","num_units":4,"style":2,"tier_current":2,"tier_total":3}],"units":[{"character_id":"TFT3_Mordekaiser","items":[],"name":"","rarity":1,"tier":2},{"character_id":"TFT3_Nautilus","items":[],"name":"","rarity":1,"tier":2},{"character_id":"TFT3_Jayce","items":[36,77,24],"name":"","rarity":2,"tier":2},{"character_id":"TFT3_Bard","items":[],"name":"","rarity":2,"tier":2},{"character_id":"TFT3_Cassiopeia","items":[44,33,55],"name":"","rarity":2,"tier":2},{"character_id":"TFT3_Karma","items":[],"name":"","rarity":2,"tier":2},{"character_id":"TFT3_Soraka","items":[],"name":"","rarity":3,"tier":2},{"character_id":"TFT3_WuKong","items":[99,9,19],"name":"","rarity":3,"tier":2}],"winPercentage":0.006329113924050633},"TFT3_Caitlyn,TFT3_Ekko,TFT3_Fiora,TFT3_Irelia,TFT3_Leona,TFT3_Thresh,TFT3_Vayne,TFT3_Vi,TFT3_WuKong":{"bottom4Percentage":0.37055837563451777,"compName":"Chrono, Cybernetic, Blademaster","placements":[1,6,3,2,1,3,5,3,1,1,2,1,3,1,3,3,1,1,5,2,1,3,2,2,2,1,1,2,3,1,5,2,2,3,4,2,5,1,3,4,1,2,4,2,3,3,3,5,1,1,4,3,5,1,3,5,6,1,5,1,1,1,3,2,2,4,3,4,3,1,1,3,4,5,1,3,1,3,1,2,4,3,4,1,1,2,1,1,1,1,3,1,1,6,3,4,6,2,4,4,2,1,4,1,1,4,2,2,2,1,4,3,5,2,1,5,2,6,2,6,1,2,2,1,1,1,1,1,2,1,1,1,2,1,2,2,3,1,6,1,2,4,2,1,4,6,7,2,3,5,3,1,1,1,3,1,6,1,1,1,1,4,1,3,1,1,2,1,3,2,1,1,1,1,1,2,2,4,1,4,7,3,2,1,1,2,2,1,1,1,1,5,1,1,1,3,4],"top4Percentage":0.6294416243654822,"traits":[{"name":"Chrono","num_units":3,"style":1,"tier_current":1,"tier_total":4},{"name":"Cybernetic","num_units":6,"style":3,"tier_current":2,"tier_total":2},{"name":"Infiltrator","num_units":1,"style":0,"tier_current":0,"tier_total":3},{"name":"ManaReaver","num_units":2,"style":3,"tier_current":1,"tier_total":1},{"name":"Set3_Blademaster","num_units":3,"style":1,"tier_current":1,"tier_total":3},{"name":"Set3_Brawler","num_units":1,"style":0,"tier_current":0,"tier_total":2},{"name":"Sniper","num_units":2,"style":1,"tier_current":1,"tier_total":2},{"name":"Vanguard","num_units":2,"style":1,"tier_current":1,"tier_total":3}],"units":[{"character_id":"TFT3_Fiora","items":[67],"name":"","rarity":0,"tier":2},{"character_id":"TFT3_Caitlyn","items":[],"name":"","rarity":0,"tier":2},{"character_id":"TFT3_Leona","items":[67],"name":"","rarity":0,"tier":2},{"character_id":"TFT3_Vi","items":[45],"name":"","rarity":2,"tier":2},{"character_id":"TFT3_Vayne","items":[29,12,19],"name":"","rarity":2,"tier":2},{"character_id":"TFT3_Irelia","items":[99,26,12],"name":"","rarity":3,"tier":2},{"character_id":"TFT3_WuKong","items":[36,45],"name":"","rarity":3,"tier":2},{"character_id":"TFT3_Thresh","items":[4,18],"name":"","rarity":4,"tier":1},{"character_id":"TFT3_Ekko","items":[36,17,15],"name":"","rarity":4,"tier":1}],"winPercentage":0.4010152284263959},"TFT3_Cassiopeia,TFT3_Jayce,TFT3_Karma,TFT3_Lulu,TFT3_Mordekaiser,TFT3_Nautilus,TFT3_Soraka,TFT3_Thresh,TFT3_WuKong":{"bottom4Percentage":0.4381625441696113,"compName":"Mystic, Vanguard","placements":[6,3,2,2,3,3,3,1,4,4,1,1,1,2,2,2,5,5,2,3,2,1,2,3,1,4,6,2,3,3,4,3,2,1,1,2,3,3,3,2,5,4,2,1,5,4,6,3,3,6,6,1,6,1,1,2,3,1,2,6,2,1,3,1,5,2,1,1,5,1,3,3,5,1,2,4,1,2,3,2,1,1,2,1,4,3,3,6,3,3,2,1,1,3,2,2,4,5,2,1,3,1,3,1,1,1,4,5,1,2,4,3,1,3,4,1,3,1,2,2,1,2,4,2,3,6,1,3,3,2,1,1,1,2,4,1,5,2,4,2,1,3,2,6,6,1,1,6,5,6,3,2,5,3,6,4,2,2,2,1,3,4,3,3,2,1,6,4,4,3,5,1,1,5,1,1,2,1,3,1,4,2,1,2,1,4,2,1,2,2,2,1,5,2,4,4,3,2,2,2,1,3,4,4,5,2,4,1,1,3,4,7,2,1,1,1,2,2,5,2,1,3,1,1,1,4,4,1,5,1,4,3,5,2,4,3,1,2,2,1,3,6,2,5,4,4,4,1,8,1,1,2,1,1,1,3,2,3,3,6,3,1,3,1,3,2,1,2,2,3,2,3,1,1,1,2,2,2,1,1,2,2,1,2,5,1,1,1,1,2,5,2,5,1,4,2,2,3,4,2,6,3,1,1,1,4,1,4,1,1,1,1,1,5,3,3,1,3,3,2,1,1,1,1,1,1,3,1,2,1,2,3,1,3,2,1,1,2,1,7,4,6,2,3,2,1,1,2,1,4,2,3,4,4,4,1,3,1,2,3,3,1,4,5,3,1,2,2,2,4,3,7,3,2,4,2,2,3,6,5,2,5,1,2,3,1,1,2,2,1,1,2,1,3,1,1,3,3,1,1,1,2,5,1,2,2,2,2,4,1,1,2,4,3,1,1,1,5,3,3,1,1,2,4,2,6,1,1,1,1,3,2,2,1,2,3,1,1,1,2,1,5,4,1,1,5,1,2,3,3,2,1,5,5,5,4,7,2,4,1,2,5,3,1,3,1,1,1,1,4,1,1,1,1,1,3,2,5,2,1,5,1,3,2,3,7,2,1,4,2,3,1,3,2,3,2,2,3,3,1,2,4,1,1,2,3,2,1,2,1,1,2,2,5,1,4,3,1,3,2,1,3,1,3,1,1,1,1,2,1,2,5,2,1,3,1,2,3,2,3,1,2,2,5,1,2,2,3,5,4,1,2,2,1,1,2,6,1,6,2,3,3,3,1,4,2,4,1,2,1,1,1,1,3,1,3,2,6,2,4,2,2,4,4,7,8,4,4,6,3,2,1,1,3,3,4,2,2,2,2,6,4,1,3,1,3,3,1,2,1,2,1,1,1,2,4,1,2,1,1,1,1,4,2,1,3,2,6,6,2,1,4,1,2,2,1,1,3,1,3,3,6,2,1,3,3,1,2,2,1,2,5,1,4,1,3,1,2,2,2,2,3,2,7,1,1,1,2,4,3,5,2,2,2,2,1,2,1,4,3,1,2,5,2,1,3,3,5,2,7,3,5,4,5,1,3,6,2,2,5,2,6,1,1,7,2,2,1,7,1,3,3,1,3,5,1,2,1,1,1,1,1,2,1,2,1,1,2,6,1,2,1,1,5,2,5,2,1,3,4,1,1,6,2,3,8,3,1,6,2,1,1,1,5,3,1,6,3,2,3,5,3,3,2,4,1,1,2,1,2,1,1,1,3,4,1,2,3,2,1,1,2,1,8,3,2,2,3,1,6,1,1,1,7,1,3,5,4,2,3,2,1,2,2,2,2,1,2,3,4,3,1,1,1,3,2,3,2,3,6,1,2,5,1,8,1,4,1,1,4,2,2,1,1,3,1,2,1,2,3,3,4,6,1,4,2,4,2,4],"top4Percentage":0.5618374558303887,"traits":[{"name":"Astro","num_units":1,"style":0,"tier_current":0,"tier_total":1},{"name":"Battlecast","num_units":1,"style":0,"tier_current":0,"tier_total":4},{"name":"Chrono","num_units":2,"style":1,"tier_current":1,"tier_total":4},{"name":"DarkStar","num_units":2,"style":1,"tier_current":1,"tier_total":4},{"name":"ManaReaver","num_units":1,"style":0,"tier_current":0,"tier_total":1},{"name":"Set3_Celestial","num_units":1,"style":0,"tier_current":0,"tier_total":3},{"name":"Set3_Mystic","num_units":4,"style":3,"tier_current":2,"tier_total":2},{"name":"SpacePirate","num_units":1,"style":0,"tier_current":0,"tier_total":2},{"name":"StarGuardian","num_units":1,"style":0,"tier_current":0,"tier_total":3},{"name":"Vanguard","num_units":4,"style":2,"tier_current":2,"tier_total":3}],"units":[{"character_id":"TFT3_Mordekaiser","items":[],"name":"","rarity":1,"tier":2},{"character_id":"TFT3_Nautilus","items":[],"name":"","rarity":1,"tier":2},{"character_id":"TFT3_Jayce","items":[36,55,39],"name":"","rarity":2,"tier":2},{"character_id":"TFT3_Cassiopeia","items":[44,22,37],"name":"","rarity":2,"tier":2},{"character_id":"TFT3_Karma","items":[],"name":"","rarity":2,"tier":2},{"character_id":"TFT3_Soraka","items":[],"name":"","rarity":3,"tier":2},{"character_id":"TFT3_WuKong","items":[],"name":"","rarity":3,"tier":2},{"character_id":"TFT3_Thresh","items":[14,79],"name":"","rarity":4,"tier":1},{"character_id":"TFT3_Lulu","items":[],"name":"","rarity":4,"tier":2}],"winPercentage":0.33451118963486454},"TFT3_Cassiopeia,TFT3_Jayce,TFT3_Karma,TFT3_Lulu,TFT3_Mordekaiser,TFT3_Nautilus,TFT3_Soraka,TFT3_WuKong":{"bottom4Percentage":0.20502092050209206,"compName":"Mystic, Vanguard","placements":[5,5,7,5,6,7,5,1,6,1,6,4,6,8,7,2,8,5,5,7,7,6,7,7,8,8,6,7,5,4,8,8,5,6,8,7,8,4,4,7,8,6,6,4,5,4,2,7,8,4,7,7,8,6,4,4,3,7,7,8,3,5,4,5,7,5,6,4,7,3,7,7,8,6,7,1,6,8,3,8,5,6,8,3,4,7,7,5,6,4,8,4,2,5,6,3,7,7,3,5,3,6,4,4,8,3,5,3,6,7,7,8,2,8,4,8,5,1,3,7,2,8,3,6,4,7,8,4,8,4,3,4,1,4,5,3,4,7,3,5,6,5,3,8,8,2,6,6,3,8,1,3,2,6,2,5,7,7,2,3,2,2,5,2,3,5,6,3,2,6,7,2,5,5,5,6,2,5,6,2,6,7,3,7,3,6,4,3,5,7,7,6,5,2,5,6,7,4,4,4,3,5,5,8,5,8,5,1,7,8,7,5,4,3,6,4,7,7,4,5,7,8,8,4,7,2,3,2,4,7,3,6,1,8,2,4,5,5,3],"top4Percentage":0.7949790794979079,"traits":[{"name":"Astro","num_units":1,"style":0,"tier_current":0,"tier_total":1},{"name":"Battlecast","num_units":1,"style":0,"tier_current":0,"tier_total":4},{"name":"Chrono","num_units":1,"style":0,"tier_current":0,"tier_total":4},{"name":"DarkStar","num_units":2,"style":1,"tier_current":1,"tier_total":4},{"name":"Set3_Celestial","num_units":1,"style":0,"tier_current":0,"tier_total":3},{"name":"Set3_Mystic","num_units":4,"style":3,"tier_current":2,"tier_total":2},{"name":"SpacePirate","num_units":1,"style":0,"tier_current":0,"tier_total":2},{"name":"StarGuardian","num_units":1,"style":0,"tier_current":0,"tier_total":3},{"name":"Vanguard","num_units":4,"style":2,"tier_current":2,"tier_total":3}],"units":[{"character_id":"TFT3_Mordekaiser","items":[],"name":"","rarity":1,"tier":2},{"character_id":"TFT3_Nautilus","items":[],"name":"","rarity":1,"tier":2},{"character_id":"TFT3_Jayce","items":[36,15,59],"name":"","rarity":2,"tier":2},{"character_id":"TFT3_Cassiopeia","items":[44,37,22],"name":"","rarity":2,"tier":2},{"character_id":"TFT3_Karma","items":[],"name":"","rarity":2,"tier":2},{"character_id":"TFT3_Soraka","items":[],"name":"","rarity":3,"tier":2},{"character_id":"TFT3_WuKong","items":[57],"name":"","rarity":3,"tier":2},{"character_id":"TFT3_Lulu","items":[],"name":"","rarity":4,"tier":1}],"winPercentage":0.03347280334728033},"TFT3_Ekko,TFT3_Fiora,TFT3_Irelia,TFT3_Leona,TFT3_Riven,TFT3_Thresh,TFT3_Vayne,TFT3_Vi":{"bottom4Percentage":0.25757575757575757,"compName":"Cybernetic, Blademaster","placements":[5,3,3,6,3,4,4,4,6,2,7,1,3,4,3,4,1,2,2,7,3,4,6,5,3,4,5,3,6,7,7,5,6,6,8,2,7,5,4,7,5,5,4,6,5,2,4,4,8,8,7,6,6,2,8,2,2,3,6,5,6,6,4,6,2,5,5,5,7,4,5,2,5,7,2,2,4,2,3,2,6,4,8,8,7,8,2,5,3,5,3,8,7,6,4,2,4,6,6,5,5,5,5,6,4,3,5,2,7,1,1,4,8,1,7,6,7,3,1,6,4,5,2,4,8,2,1,6,7,8,3,5],"top4Percentage":0.7424242424242424,"traits":[{"name":"Chrono","num_units":2,"style":1,"tier_current":1,"tier_total":4},{"name":"Cybernetic","num_units":6,"style":3,"tier_current":2,"tier_total":2},{"name":"Infiltrator","num_units":1,"style":0,"tier_current":0,"tier_total":3},{"name":"ManaReaver","num_units":2,"style":3,"tier_current":1,"tier_total":1},{"name":"Set3_Blademaster","num_units":3,"style":1,"tier_current":1,"tier_total":3},{"name":"Set3_Brawler","num_units":1,"style":0,"tier_current":0,"tier_total":2},{"name":"Sniper","num_units":1,"style":0,"tier_current":0,"tier_total":2},{"name":"Vanguard","num_units":1,"style":0,"tier_current":0,"tier_total":3}],"units":[{"character_id":"TFT3_Fiora","items":[47],"name":"","rarity":0,"tier":2},{"character_id":"TFT3_Leona","items":[27],"name":"","rarity":0,"tier":2},{"character_id":"TFT3_Vi","items":[67],"name":"","rarity":2,"tier":2},{"character_id":"TFT3_Vayne","items":[29,19],"name":"","rarity":2,"tier":2},{"character_id":"TFT3_Irelia","items":[29],"name":"","rarity":3,"tier":2},{"character_id":"TFT3_Riven","items":[],"name":"","rarity":3,"tier":2},{"character_id":"TFT3_Thresh","items":[],"name":"","rarity":4,"tier":1},{"character_id":"TFT3_Ekko","items":[25,57,47],"name":"","rarity":4,"tier":1}],"winPercentage":0.05303030303030303},"TFT3_Ekko,TFT3_Fiora,TFT3_Irelia,TFT3_Leona,TFT3_Riven,TFT3_Thresh,TFT3_Vayne,TFT3_Vi,TFT3_WuKong":{"bottom4Percentage":0.43820224719101125,"compName":"Chrono, Cybernetic, Blademaster","placements":[1,4,1,1,1,3,5,1,1,2,1,2,3,3,2,1,7,3,2,1,1,2,5,1,3,5,4,5,1,2,1,2,1,2,1,1,1,1,2,1,5,3,2,3,4,1,1,4,3,5,1,1,2,1,4,5,3,2,6,5,2,5,1,1,1,2,1,1,2,3,3,4,1,2,4,3,3,4,2,2,1,1,2,4,3,4,2,4,6,2,2,4,3,2,1,1,2,2,3,3,5,5,5,3,8,4,3,1,1,3,4,4,3,1,2,2,5,3,3,3,3,5,3,3,2,4,4,6,3,5,5,1,3,4,1,2,2,2,2,1,1,1,1,4,1,6,2,1,2,5,2,2,1,1,3,5,3,1,5,2,2,1,1,1,2,4,5,3,3,3,2,3,2,4,8,2,1,3],"top4Percentage":0.5617977528089888,"traits":[{"name":"Battlecast","num_units":0,"style":0,"tier_current":0,"tier_total":4},{"name":"Chrono","num_units":3,"style":1,"tier_current":1,"tier_total":4},{"name":"Cybernetic","num_units":6,"style":3,"tier_current":2,"tier_total":2},{"name":"Infiltrator","num_units":1,"style":0,"tier_current":0,"tier_total":3},{"name":"ManaReaver","num_units":2,"style":3,"tier_current":1,"tier_total":1},{"name":"MechPilot","num_units":0,"style":0,"tier_current":0,"tier_total":1},{"name":"Protector","num_units":0,"style":0,"tier_current":0,"tier_total":3},{"name":"Set3_Blademaster","num_units":3,"style":1,"tier_current":1,"tier_total":3},{"name":"Set3_Brawler","num_units":1,"style":0,"tier_current":0,"tier_total":2},{"name":"Sniper","num_units":1,"style":0,"tier_current":0,"tier_total":2},{"name":"Vanguard","num_units":2,"style":1,"tier_current":1,"tier_total":3}],"units":[{"character_id":"TFT3_Fiora","items":[36],"name":"","rarity":0,"tier":2},{"character_id":"TFT3_Leona","items":[59],"name":"","rarity":0,"tier":2},{"character_id":"TFT3_Vi","items":[59],"name":"","rarity":2,"tier":2},{"character_id":"TFT3_Vayne","items":[],"name":"","rarity":2,"tier":2},{"character_id":"TFT3_Irelia","items":[19,29,49],"name":"","rarity":3,"tier":2},{"character_id":"TFT3_WuKong","items":[],"name":"","rarity":3,"tier":2},{"character_id":"TFT3_Riven","items":[],"name":"","rarity":3,"tier":2},{"character_id":"TFT3_Thresh","items":[],"name":"","rarity":4,"tier":1},{"character_id":"TFT3_Ekko","items":[39,57,36],"name":"","rarity":4,"tier":2}],"winPercentage":0.29213483146067415}}